jijmodeling-1.14.1.dist-info/METADATA
jijmodeling-1.14.1.dist-info/WHEEL
jijmodeling-1.14.1.dist-info/licenses/LICENSE.txt
jijmodeling/__init__.py
jijmodeling/__init__.pyi
jijmodeling/_jijmodeling.pyd
jijmodeling/experimental.py
jijmodeling/experimental.pyi
jijmodeling/py.typed
jijmodeling/range/__init__.py
jijmodeling/range/__init__.pyi
jijmodeling/range/size.py
jijmodeling/range/size.pyi
jijmodeling/range/value.py
jijmodeling/range/value.pyi
jijmodeling-1.14.1.dist-info/RECORD
