Metadata-Version: 2.4
Name: jijmodeling
Version: 1.14.1
Classifier: Development Status :: 5 - Production/Stable
Classifier: Operating System :: POSIX :: Linux
Classifier: Operating System :: MacOS
Classifier: Operating System :: Microsoft :: Windows
Classifier: Programming Language :: Rust
Classifier: Programming Language :: Python
Classifier: Programming Language :: Python :: 3
Classifier: Programming Language :: Python :: 3 :: Only
Classifier: Programming Language :: Python :: 3.9
Classifier: Programming Language :: Python :: 3.10
Classifier: Programming Language :: Python :: 3.11
Classifier: Programming Language :: Python :: 3.12
Classifier: Programming Language :: Python :: 3.13
Classifier: Programming Language :: Python :: Implementation :: CPython
Classifier: License :: Other/Proprietary License
Classifier: Topic :: Scientific/Engineering :: Mathematics
Requires-Dist: numpy
Requires-Dist: pandas
Requires-Dist: orjson>=3.8.0,<4.0.0
Requires-Dist: ommx>=2.0.0,<3.0.0
Requires-Dist: typing-extensions
License-File: LICENSE.txt
Summary: Mathematical modeling tool for optimization problem
Author: Jij Inc.
Author-email: info@j-ij.com
Requires-Python: >=3.9, <3.14
Project-URL: Homepage, https://www.jijzept.com
